as_service.py
as_service-0.1.1.dist-info/LICENSE
as_service-0.1.1.dist-info/METADATA
as_service-0.1.1.dist-info/WHEEL
as_service-0.1.1.dist-info/top_level.txt
as_service-0.1.1.dist-info/RECORD
